kneed/__init__.py
kneed/_version.py
kneed/data_generator.py
kneed/knee_locator.py
kneed/shape_detector.py
kneed-0.8.3.dist-info/METADATA
kneed-0.8.3.dist-info/WHEEL
kneed-0.8.3.dist-info/licenses/LICENSE
kneed-0.8.3.dist-info/RECORD
