Metadata-Version: 2.1
Name: kneed
Version: 0.8.3
Summary: Knee-point detection in Python
Project-URL: Homepage, https://github.com/arvkevi/kneed
Project-URL: Documentation, https://kneed.readthedocs.io/en/latest/
Author-email: Kevin Arvai <arvkevi@gmail.com>
License-File: LICENSE
Keywords: elbow-method,knee-detection,system
Classifier: Development Status :: 3 - Alpha
Classifier: Intended Audience :: Science/Research
Classifier: Programming Language :: Python :: 3
Classifier: Topic :: Scientific/Engineering :: Information Analysis
Requires-Python: >=3.5
Requires-Dist: numpy>=1.14.2
Requires-Dist: scipy>=1.0.0
Provides-Extra: plot
Requires-Dist: matplotlib>=2.2.5; extra == 'plot'
Provides-Extra: testing
Requires-Dist: matplotlib>=2.2.5; extra == 'testing'
Requires-Dist: pytest-cov>=3.0.0; extra == 'testing'
Requires-Dist: pytest>=5.0.1; extra == 'testing'
